hoppet-2.2.0.dist-info/WHEEL
hoppet-2.2.0.dist-info/METADATA
hoppet-2.2.0.dist-info/RECORD
hoppet-2.2.0.dist-info/licenses/AUTHORS.md
hoppet-2.2.0.dist-info/licenses/LICENSE
lib64/libhoppet.so.0.0.0
lib64/libhoppet.so
lib64/libhoppet.a
hoppet/lhapdf.py
hoppet/__init__.py
hoppet/_hoppet_swig.cpython-311-x86_64-linux-gnu.so
bin/hoppet-config
hoppet.libs/libquadmath-96973f99.so.0.0.0
hoppet.libs/libgfortran-040039e1.so.5.0.0
include/hoppet.h
include/hoppet/xc2ns3p.mod
include/hoppet/sf_nnlo_e_rename.mod
include/hoppet/splitting_functions_n3lo_e.mod
include/hoppet/interpolation.mod
include/hoppet/sf_nnlo_n_rename.mod
include/hoppet/momnsmod.mod
include/hoppet/integrator.mod
include/hoppet/xpns3p.mod
include/hoppet/xpns2n.mod
include/hoppet/sort.mod
include/hoppet/sf_n3lo_p_rename.mod
include/hoppet/assertions.mod
include/hoppet/convolution_pieces.mod
include/hoppet/splitting_functions.mod
include/hoppet/xpns2p.mod
include/hoppet/convolution.mod
include/hoppet/xc2ns2p.mod
include/hoppet/xcdiff2e.mod
include/hoppet/structure_functions.mod
include/hoppet/pdf_representation.mod
include/hoppet/consts_dp.mod
include/hoppet/xclsg2e.mod
include/hoppet/xc2sg2e.mod
include/hoppet/hoppet_probes.mod
include/hoppet/xclns2p.mod
include/hoppet/dglap_holders.mod
include/hoppet/runge_kutta.mod
include/hoppet/xcdiff3p.mod
include/hoppet/couplings.mod
include/hoppet/xpgq3a.mod
include/hoppet/xpns3m.mod
include/hoppet/hoppetrandom.mod
include/hoppet/hoppet_mass_threshold_mat.mod
include/hoppet/splitting_functions_n3lo.mod
include/hoppet/splitting_functions_n3lo_n.mod
include/hoppet/hoppet_git_state.mod
include/hoppet/xclgl3e.mod
include/hoppet/aqqpss3_mod.mod
include/hoppet/pdf_tabulate.mod
include/hoppet/xclsg2p.mod
include/hoppet/xclns3p.mod
include/hoppet/xpgq3a_2404.mod
include/hoppet/xpij2e.mod
include/hoppet/new_as.mod
include/hoppet/xc2ps3e.mod
include/hoppet/streamlined_interface.mod
include/hoppet/xpns3s.mod
include/hoppet/hoppet_lhapdf_interfaces.mod
include/hoppet/coefficient_functions_holder_internal.mod
include/hoppet/xpgg3a_2410.mod
include/hoppet/coefficient_functions.mod
