Metadata-Version: 2.2
Name: HOPPET
Version: 2.2.0
Summary: HOPPET: A Higher Order Perturbative Parton Evolution Toolkit
Keywords: physics,pdf,evolution
Author: Frederic Dreyer, Alexander Karlberg, Paolo Nason, Juan Rojo, Gavin Salam, Giulia Zanderighi
Author-Email: Alexander Karlberg <alexander.karlberg@cern.ch>, Gavin Salam <gavin.salam@physics.ox.ac.uk>
License: GPL-3.0-or-later
Classifier: Development Status :: 4 - Beta
Classifier: Intended Audience :: Science/Research
Classifier: Programming Language :: Python :: 3
Classifier: Topic :: Scientific/Engineering :: Physics
Project-URL: Homepage, https://github.com/hoppet-code
Project-URL: Documentation, https://hoppet-code.github.io/hoppet/
Project-URL: Repository, https://github.com/hoppet-code/hoppet
Project-URL: Changelog, https://github.com/hoppet-code/hoppet/blob/master/NEWS.md
Requires-Python: >=3.8
Requires-Dist: numpy
